LICENSE.md
README.md
setup.cfg
setup.py
nifti2gif/__init__.py
nifti2gif/__main__.py
nifti2gif/config.py
nifti2gif/core.py
nifti2gif.egg-info/PKG-INFO
nifti2gif.egg-info/SOURCES.txt
nifti2gif.egg-info/dependency_links.txt
nifti2gif.egg-info/entry_points.txt
nifti2gif.egg-info/not-zip-safe
nifti2gif.egg-info/requires.txt
nifti2gif.egg-info/top_level.txt