Metadata-Version: 2.1
Name: nifti2gif
Version: 0.0.4
Summary: Create GIF from NIfTI image.
Home-page: https://github.com/mikbuch/nifti2gif
Author: Mikolaj Buchwald
Author-email: mikolaj.buchwald@gmail.com
License: BSD 3-Clause License
Keywords: nifti,gif
License-File: LICENSE.md
